convert_csv_to_json/__init__.py
convert_csv_to_json/csv_parser.py
convert_csv_to_json-0.2.dist-info/DESCRIPTION.rst
convert_csv_to_json-0.2.dist-info/METADATA
convert_csv_to_json-0.2.dist-info/RECORD
convert_csv_to_json-0.2.dist-info/WHEEL
convert_csv_to_json-0.2.dist-info/metadata.json
convert_csv_to_json-0.2.dist-info/top_level.txt
