Metadata-Version: 2.0
Name: convert-csv-to-json
Version: 0.2
Summary: directly convert csv to json
Home-page: https://github.com/zbagdzevicius/convert_csv_to_json
Author: Zygimantas Bagdzevicius
Author-email: zbagdzevicius@gmail.com
License: UNKNOWN
Platform: UNKNOWN
Classifier: Programming Language :: Python :: 3
Classifier: License :: OSI Approved :: MIT License
Classifier: Operating System :: OS Independent
